pytest_isolate_mpi/__init__.py
pytest_isolate_mpi/_constants.py
pytest_isolate_mpi/_fixturecache.py
pytest_isolate_mpi/_helpers.py
pytest_isolate_mpi/_plugin.py
pytest_isolate_mpi/_subsession.py
pytest_isolate_mpi/fixtures.py
pytest_isolate_mpi-0.3.dist-info/LICENSE
pytest_isolate_mpi-0.3.dist-info/METADATA
pytest_isolate_mpi-0.3.dist-info/WHEEL
pytest_isolate_mpi-0.3.dist-info/entry_points.txt
pytest_isolate_mpi-0.3.dist-info/top_level.txt
pytest_isolate_mpi-0.3.dist-info/RECORD
