Metadata-Version: 2.2
Name: pytest-isolate-mpi
Version: 0.3
Summary: pytest-isolate-mpi allows for MPI-parallel tests being executed in a segfault and MPI_Abort safe manner
Author-email: Sebastian Gottfried <sebastian.gottfried@dlr.de>, Jordan Lavialle <jordan.j.lavialle@airbus.com>, Immo Huismann <immo.huismann@dlr.de>
License: BSD 3-Clause License
Project-URL: Documentation, http://pytest-isolate-mpi.readthedocs.io/
Project-URL: Repository, https://github.com/dlr-sp/pytest-isolate-mpi
Project-URL: Bug Tracker, https://github.com/dlr-sp/pytest-isolate-mpi/issues
Project-URL: Changelog, https://github.com/dlr-sp/pytest-isolate-mpi/blob/main/CHANGES.rst
Classifier: Development Status :: 4 - Beta
Classifier: Programming Language :: Python
Classifier: Framework :: Pytest
Requires-Python: >=3.8
License-File: LICENSE
Requires-Dist: pytest>=5
Requires-Dist: mpi4py
Provides-Extra: dev
Requires-Dist: check-manifest; extra == "dev"
Requires-Dist: Sphinx<7; extra == "dev"
Requires-Dist: sphinx-rtd-theme<2; extra == "dev"
Requires-Dist: docutils<0.19; extra == "dev"
Requires-Dist: pylint; extra == "dev"
Requires-Dist: pytest-cov; extra == "dev"
Requires-Dist: wheel; extra == "dev"
Requires-Dist: black; extra == "dev"
Requires-Dist: pycodestyle; extra == "dev"
Requires-Dist: watchdog; extra == "dev"
